fake_api_server/ci/__init__.py
fake_api_server/ci/surveillance/__init__.py
fake_api_server/ci/surveillance/__pkg_info__.py
fake_api_server/ci/surveillance/_static/pr-body.md
fake_api_server/ci/surveillance/component/__init__.py
fake_api_server/ci/surveillance/component/git.py
fake_api_server/ci/surveillance/component/github_opt.py
fake_api_server/ci/surveillance/log.py
fake_api_server/ci/surveillance/model/__init__.py
fake_api_server/ci/surveillance/model/_base.py
fake_api_server/ci/surveillance/model/action.py
fake_api_server/ci/surveillance/model/compare.py
fake_api_server/ci/surveillance/model/config/__init__.py
fake_api_server/ci/surveillance/model/config/api_config.py
fake_api_server/ci/surveillance/model/config/git.py
fake_api_server/ci/surveillance/model/config/github.py
fake_api_server/ci/surveillance/model/config/github_action.py
fake_api_server/ci/surveillance/runner.py
fake_api_server_surveillance-0.2.0.dist-info/LICENSE
fake_api_server_surveillance-0.2.0.dist-info/METADATA
fake_api_server_surveillance-0.2.0.dist-info/WHEEL
fake_api_server_surveillance-0.2.0.dist-info/entry_points.txt
fake_api_server_surveillance-0.2.0.dist-info/RECORD
