Metadata-Version: 2.3
Name: fake-api-server-surveillance
Version: 0.2.0
Summary: 🤖 A CI tool for monitoring a specific API end points and keeping fake API server always up-to-date.
License: MIT
Keywords: fake,API,fake server,fake API server,web,server,surveillance,monitor
Author: Liu, Bryant
Author-email: chi10211201@cycu.org.tw
Requires-Python: >=3.9,<3.13
Classifier: Development Status :: 3 - Alpha
Classifier: Intended Audience :: Developers
Classifier: Topic :: Internet
Classifier: Topic :: Utilities
Classifier: Topic :: Software Development :: Libraries :: Python Modules
Classifier: Topic :: Software Development :: Testing :: Mocking
Classifier: Topic :: Internet :: WWW/HTTP
Classifier: Topic :: Internet :: WWW/HTTP :: HTTP Servers
Classifier: Topic :: Internet :: WWW/HTTP :: Dynamic Content
Classifier: License :: OSI Approved :: MIT License
Classifier: Operating System :: OS Independent
Classifier: Environment :: Console
Classifier: Programming Language :: Python :: 3
Classifier: Programming Language :: Python :: 3.9
Classifier: Programming Language :: Python :: 3.10
Classifier: Programming Language :: Python :: 3.11
Classifier: Programming Language :: Python :: 3.12
Classifier: Programming Language :: Python :: 3.13
Requires-Dist: PyYAML (>=6.0)
Requires-Dist: fake-api-server[mini] (>=0.4.0,<0.5.0)
Requires-Dist: gitpython (>=3.1.44,<4.0.0)
Requires-Dist: pygithub (>=2.6.1,<3.0.0)
Project-URL: Changelog, https://chisanan232.github.io/PyFake-API-Server-Surveillance/latest/release_note/
Project-URL: Documentation, https://chisanan232.github.io/PyFake-API-Server-Surveillance/stable/
Project-URL: Homepage, https://github.com/Chisanan232/PyFake-API-Server-Surveillance
Project-URL: Project Management, https://app.clickup.com/9018752317/v/f/90183127005/90182605225
Project-URL: Repository, https://github.com/Chisanan232/PyFake-API-Server-Surveillance
